README.txt
setup.py
Products/__init__.py
Products.NuPlone.egg-info/PKG-INFO
Products.NuPlone.egg-info/SOURCES.txt
Products.NuPlone.egg-info/dependency_links.txt
Products.NuPlone.egg-info/namespace_packages.txt
Products.NuPlone.egg-info/not-zip-safe
Products.NuPlone.egg-info/requires.txt
Products.NuPlone.egg-info/top_level.txt
Products/NuPlone/__init__.py
Products/NuPlone/configure.zcml
Products/NuPlone/interfaces.py
Products/NuPlone/nuplone images.psd
Products/NuPlone/profiles.zcml
Products/NuPlone/setuphandlers.py
Products/NuPlone/version.txt
Products/NuPlone/profiles/default/cssregistry.xml
Products/NuPlone/profiles/default/import_steps.xml
Products/NuPlone/profiles/default/jsregistry.xml
Products/NuPlone/profiles/default/metadata.xml
Products/NuPlone/profiles/default/nuplone_various.txt
Products/NuPlone/profiles/default/portlets.xml
Products/NuPlone/profiles/default/skins.xml
Products/NuPlone/profiles/default/viewlets.xml
Products/NuPlone/skins/nuplone_images/body-ltr.gif
Products/NuPlone/skins/nuplone_images/body-rtl.gif
Products/NuPlone/skins/nuplone_images/breadCrumbDivider-rtl.gif
Products/NuPlone/skins/nuplone_images/breadCrumbDivider.gif
Products/NuPlone/skins/nuplone_images/bulletLeft.gif
Products/NuPlone/skins/nuplone_images/bulletRight.gif
Products/NuPlone/skins/nuplone_images/buttonBack-over.png
Products/NuPlone/skins/nuplone_images/buttonBack.png
Products/NuPlone/skins/nuplone_images/buttonForward-over.png
Products/NuPlone/skins/nuplone_images/buttonForward.png
Products/NuPlone/skins/nuplone_images/contentViewsColour.gif
Products/NuPlone/skins/nuplone_images/currentNav-rtl.gif
Products/NuPlone/skins/nuplone_images/currentNav.gif
Products/NuPlone/skins/nuplone_images/edgeColour.gif
Products/NuPlone/skins/nuplone_images/grid.png
Products/NuPlone/skins/nuplone_images/header.gif
Products/NuPlone/skins/nuplone_images/listBox-bottom.gif
Products/NuPlone/skins/nuplone_images/listBox-header-left.gif
Products/NuPlone/skins/nuplone_images/listBox-header-right.gif
Products/NuPlone/skins/nuplone_images/listBox-top.gif
Products/NuPlone/skins/nuplone_images/logo-rtl.gif
Products/NuPlone/skins/nuplone_images/logo.gif
Products/NuPlone/skins/nuplone_images/pageTabs-bottom-left-over.gif
