Metadata-Version: 1.0
Name: Products.NuPlone
Version: 1.0b2
Summary: A new theme for Plone 3.0
Home-page: http://plone.org/
Author: Cornelis Kolbach and Alexander Limi
Author-email: plone-developers@lists.sourceforge.net
License: GPL
Keywords: Plone theme tableless
Platform: UNKNOWN
Classifier: Framework :: Plone
Classifier: License :: OSI Approved :: GNU General Public License (GPL)
Classifier: Operating System :: OS Independent
Classifier: Topic :: Software Development :: User Interfaces
